beansoup/__init__.py
beansoup/transactions.py
beansoup/version.py
beansoup-1.0a6.dist-info/LICENSE
beansoup-1.0a6.dist-info/METADATA
beansoup-1.0a6.dist-info/WHEEL
beansoup-1.0a6.dist-info/top_level.txt
beansoup-1.0a6.dist-info/RECORD
