Metadata-Version: 2.1
Name: beansoup
Version: 1.0a6
Summary: A companion to beancount, a command-line double-entry accounting tool
Home-page: https://github.com/fxtlabs/beansoup
Author: Filippo Tampieri
Author-email: fxt@fxtlabs.com
License: GPLv2
Keywords: accounting,investing
Platform: UNKNOWN
Classifier: Development Status :: 2 - Pre-Alpha
Classifier: Intended Audience :: Developers
Classifier: Intended Audience :: Financial and Insurance Industry
Classifier: Topic :: Office/Business :: Financial
Classifier: Topic :: Office/Business :: Financial :: Accounting
Classifier: Topic :: Office/Business :: Financial :: Investment
Classifier: License :: OSI Approved :: GNU General Public License v2 (GPLv2)
Classifier: Programming Language :: Python :: 3.3
Classifier: Programming Language :: Python :: 3.4
Classifier: Programming Language :: Python :: 3.5
Classifier: Operating System :: OS Independent
Requires-Dist: beancount
